CHANGES.rst
COPYING
MANIFEST.in
README.rst
setup.py
tox.ini
deploy/ansible/ansible.cfg
deploy/ansible/hosts
deploy/ansible/install.yml
deploy/ansible/provisioning-on-nodes.yml
deploy/ansible/readme.rst
deploy/ansible/start-qagent.yml
deploy/ansible/start-qmaster.yml
doc/HOWTO-run_tmp.rst
doc/HOWTO_qulolist-plots.rst
doc/devel_notes.rst
doc/linux_performance_monitoring.rst
doc/qagent.conf
doc/qulolist.rst
doc/requirements.text
examples/etc/conf.d/qulo.conf
examples/etc/qulo/qagent.conf
examples/etc/qulo/qmaster.conf
examples/etc/qulo/qulod.conf
qulo/__init__.py
qulo/conf.py
qulo/constants.py
qulo/daemon.py
qulo/error_handling.py
qulo/logs.py
qulo/maind.py
qulo/qagent.py
qulo/qmaster.py
qulo/qmessage.py
qulo/qulod.py
qulo/sensors.py
tests/__init__.py
tests/common/__init__.py
tests/common/docker.py
tests/common/init.py
tests/common/logs.py
tests/common/program.py
tests/common/readme
tests/data/qulo.conf
tests/data/qulod.conf
tests/data/qulod.conf1
tests/data/qulod.conf2
tests/functional/__init__.py
tests/functional/base_start_stop.py
tests/functional/environment.py
tests/functional/graphite.py
tests/functional/test_graphite.py
tests/functional/test_init_script.py
tests/functional/test_qagent.py
tests/functional/test_qmaster.py
tests/functional/test_qulod_start_stop.py
tests/functional/test_resilience.py
tests/functional/data/logging-test.1.conf
tests/functional/data/logging-test.2.conf
tests/functional/data/logging-test.qagent.conf
tests/functional/data/logging-test.qmaster.conf
tests/functional/data/logging-test.qulod.conf
tests/functional/data/qagent-test.1.conf
tests/functional/data/qagent-test.1.docker.conf
tests/functional/data/qagent-test.2.conf
tests/functional/data/qagent-test.3.conf
tests/functional/data/qagent-test.4.conf
tests/functional/data/qagent-test.5.conf
tests/functional/data/qagent-test.6.conf
tests/functional/data/qagent-test.7.conf
tests/functional/data/qagent-test.docker.1.conf
tests/functional/data/qagent-test.empty.conf
