Metadata-Version: 1.1
Name: QULo
Version: 1.10.0
Summary: A package to collect basic performance data from clusters
Home-page: https://itp.uni-frankfurt.de/~palao/software/QULo
Author: David Palao
Author-email: palao@csc.uni-frankfurt.de
License: GNU General Public License (GPLv3)
Platform: GNU/Linux
Classifier: Development Status :: 4 - Beta
Classifier: Environment :: Console
Classifier: Environment :: No Input/Output (Daemon)
Classifier: Framework :: AsyncIO
Classifier: Intended Audience :: System Administrators
Classifier: License :: OSI Approved :: GNU General Public License v3 (GPLv3)
Classifier: Natural Language :: English
Classifier: Operating System :: POSIX :: Linux
Classifier: Programming Language :: Python :: 3
Classifier: Programming Language :: Python :: 3.6
Classifier: Programming Language :: Python :: Implementation :: CPython
Classifier: Topic :: System :: Monitoring
Provides: qulo
